diseloryaPdf2md/__init__.py
diseloryaPdf2md/pdf2md.py
diseloryapdf2md-0.0.1.dist-info/METADATA
diseloryapdf2md-0.0.1.dist-info/WHEEL
diseloryapdf2md-0.0.1.dist-info/licenses/LICENSE
diseloryapdf2md-0.0.1.dist-info/RECORD
