Metadata-Version: 2.1
Name: diseloryaPdf2md
Version: 0.0.1
Summary: Diselorya's PDF to Markdown tool especially for Obsidian.
Project-URL: Homepage, https://github.com/Diselorya/pdf2md/
Author: Diselorya
License: Copyright (c) 2018 The Python Packaging Authority
License-File: LICENSE
Keywords: diselorya,md,obsidian,pdf,python
Classifier: Development Status :: 3 - Alpha
Classifier: Intended Audience :: Developers
Classifier: Operating System :: Microsoft :: Windows
Classifier: Programming Language :: Python :: 3
Requires-Python: >=3.8
Requires-Dist: diseloryahelper>=0.0.0.3
